<annotation>
	<folder>images</folder>
	<filename>heron-66.jpg</filename>
	<path>/Users/disla/Projects/raccoon_dataset/images/heron-66.jpg</path>
	<source>
		<database>Unknown</database>
	</source>
	<size>
		<width>1024</width>
		<height>714</height>
		<depth>3</depth>
	</size>
	<segmented>0</segmented>
	<object>
		<name>heron</name>
		<pose>Unspecified</pose>
		<truncated>1</truncated>
		<difficult>0</difficult>
		<bndbox>
			<xmin>1</xmin>
			<ymin>89</ymin>
			<xmax>863</xmax>
			<ymax>581</ymax>
		</bndbox>
	</object>
</annotation>
