<annotation>
	<folder>images</folder>
	<filename>heron-189.jpg</filename>
	<path>/Users/disla/Projects/raccoon_dataset/images/heron-189.jpg</path>
	<source>
		<database>Unknown</database>
	</source>
	<size>
		<width>400</width>
		<height>393</height>
		<depth>3</depth>
	</size>
	<segmented>0</segmented>
	<object>
		<name>heron</name>
		<pose>Unspecified</pose>
		<truncated>0</truncated>
		<difficult>0</difficult>
		<bndbox>
			<xmin>229</xmin>
			<ymin>24</ymin>
			<xmax>347</xmax>
			<ymax>220</ymax>
		</bndbox>
	</object>
</annotation>
